CHANGELOG.rst
DESCRIPTION.rst
MANIFEST.in
README.rst
setup.py
hs3/__init__.py
hs3/__main__.py
hs3/cmd.py
hs3/cmdparse.py
hs3/conf.py
hs3/init.py
hs3/parse.py
hs3/s3config.py
hs3/test_aclcleanup.py
hs3sh.egg-info/PKG-INFO
hs3sh.egg-info/SOURCES.txt
hs3sh.egg-info/dependency_links.txt
hs3sh.egg-info/entry_points.txt
hs3sh.egg-info/requires.txt
hs3sh.egg-info/top_level.txt