Metadata-Version: 2.1
Name: hs3sh
Version: 1.3.0
Summary: HS3 shell - command processor for Amazon S3 and compatibles
Home-page: https://hs3sh.readthedocs.org
Author: Thorsten Simons
Author-email: sw@snomis.eu
License: MIT
Keywords: Amazon S3 compatible HCP HS3 Hitachi Content Platform
Platform: UNKNOWN
Classifier: Development Status :: 5 - Production/Stable
Classifier: Intended Audience :: System Administrators
Classifier: Topic :: System :: Archiving
Classifier: License :: OSI Approved :: MIT License
Classifier: Programming Language :: Python :: 3
Classifier: Operating System :: OS Independent
Classifier: Natural Language :: English
